{
    "version": 1.0,
    "term": 111149,
    "notes": [
        [
            {
                "expires": 26002,
                "id": 8,
                "speed": 1
            },
            {
                "expires": 42776,
                "id": 24,
                "speed": 1
            },
            {
                "expires": 54711,
                "id": 38,
                "speed": 1
            },
            {
                "expires": 59873,
                "id": 52,
                "speed": 1
            },
            {
                "expires": 60518,
                "id": 54,
                "speed": 1
            },
            {
                "expires": 62453,
                "id": 60,
                "speed": 1
            },
            {
                "expires": 67292,
                "id": 74,
                "speed": 1
            },
            {
                "expires": 69228,
                "id": 81,
                "speed": 1
            },
            {
                "expires": 73099,
                "id": 89,
                "speed": 1
            },
            {
                "expires": 74389,
                "id": 93,
                "speed": 1
            },
            {
                "expires": 87937,
                "id": 119,
                "speed": 1
            },
            {
                "expires": 90518,
                "id": 128,
                "speed": 1
            },
            {
                "expires": 92615,
                "id": 131,
                "speed": 1
            },
            {
                "expires": 95679,
                "id": 135,
                "speed": 1
            },
            {
                "expires": 100518,
                "id": 145,
                "speed": 1
            }
        ],
        [
            {
                "expires": 18260,
                "id": 0,
                "speed": 1
            },
            {
                "expires": 20840,
                "id": 2,
                "speed": 1
            },
            {
                "expires": 22453,
                "id": 4,
                "speed": 1
            },
            {
                "expires": 23421,
                "id": 6,
                "speed": 1
            },
            {
                "expires": 26486,
                "id": 9,
                "speed": 1
            },
            {
                "expires": 28582,
                "id": 12,
                "speed": 1
            },
            {
                "expires": 31163,
                "id": 14,
                "speed": 1
            },
            {
                "expires": 35034,
                "id": 17,
                "speed": 1
            },
            {
                "expires": 37615,
                "id": 19,
                "speed": 1
            },
            {
                "expires": 40195,
                "id": 22,
                "speed": 1
            },
            {
                "expires": 44066,
                "id": 25,
                "speed": 1
            },
            {
                "expires": 47937,
                "id": 28,
                "speed": 1
            },
            {
                "expires": 49228,
                "id": 29,
                "speed": 1
            },
            {
                "expires": 49711,
                "id": 30,
                "speed": 1
            },
            {
                "expires": 50195,
                "id": 31,
                "speed": 1
            },
            {
                "expires": 54389,
                "id": 37,
                "speed": 1
            },
            {
                "expires": 55034,
                "id": 39,
                "speed": 1
            },
            {
                "expires": 56647,
                "id": 43,
                "speed": 1
            },
            {
                "expires": 57292,
                "id": 45,
                "speed": 1
            },
            {
                "expires": 57937,
                "id": 47,
                "speed": 1
            },
            {
                "expires": 58260,
                "id": 48,
                "speed": 1
            },
            {
                "expires": 59550,
                "id": 51,
                "speed": 1
            },
            {
                "expires": 60195,
                "id": 53,
                "speed": 1
            },
            {
                "expires": 60840,
                "id": 55,
                "speed": 1
            },
            {
                "expires": 61163,
                "id": 56,
                "speed": 1
            },
            {
                "expires": 61486,
                "id": 57,
                "speed": 1
            },
            {
                "expires": 62776,
                "id": 61,
                "speed": 1
            },
            {
                "expires": 63099,
                "id": 62,
                "speed": 1
            },
            {
                "expires": 65357,
                "id": 67,
                "speed": 1
            },
            {
                "expires": 66002,
                "id": 69,
                "speed": 1
            },
            {
                "expires": 66324,
                "id": 71,
                "speed": 1
            },
            {
                "expires": 66647,
                "id": 72,
                "speed": 1
            },
            {
                "expires": 67937,
                "id": 76,
                "speed": 1
            },
            {
                "expires": 68582,
                "id": 78,
                "speed": 1
            },
            {
                "expires": 68744,
                "id": 79,
                "speed": 1
            },
            {
                "expires": 69873,
                "id": 83,
                "speed": 1
            },
            {
                "expires": 71163,
                "id": 85,
                "speed": 1
            },
            {
                "expires": 72453,
                "id": 87,
                "speed": 1
            },
            {
                "expires": 73744,
                "id": 91,
                "speed": 1
            },
            {
                "expires": 75034,
                "id": 95,
                "speed": 1
            },
            {
                "expires": 76324,
                "id": 97,
                "speed": 1
            },
            {
                "expires": 77615,
                "id": 99,
                "speed": 1
            },
            {
                "expires": 78582,
                "id": 102,
                "speed": 1
            },
            {
                "expires": 79550,
                "id": 105,
                "speed": 1
            },
            {
                "expires": 80840,
                "id": 107,
                "speed": 1
            },
            {
                "expires": 82131,
                "id": 109,
                "speed": 1
            },
            {
                "expires": 83421,
                "id": 111,
                "speed": 1
            },
            {
                "expires": 84389,
                "id": 113,
                "speed": 1
            },
            {
                "expires": 84711,
                "id": 114,
                "speed": 1
            },
            {
                "expires": 86002,
                "id": 116,
                "speed": 1
            },
            {
                "expires": 87292,
                "id": 118,
                "speed": 1
            },
            {
                "expires": 88260,
                "id": 120,
                "speed": 1
            },
            {
                "expires": 89389,
                "id": 124,
                "speed": 1
            },
            {
                "expires": 89873,
                "id": 126,
                "speed": 1
            },
            {
                "expires": 91163,
                "id": 129,
                "speed": 1
            },
            {
                "expires": 94711,
                "id": 132,
                "speed": 1
            },
            {
                "expires": 95357,
                "id": 134,
                "speed": 1
            },
            {
                "expires": 96324,
                "id": 137,
                "speed": 1
            },
            {
                "expires": 96647,
                "id": 138,
                "speed": 1
            },
            {
                "expires": 97292,
                "id": 142,
                "speed": 1
            },
            {
                "expires": 97937,
                "id": 143,
                "speed": 1
            },
            {
                "expires": 101808,
                "id": 146,
                "speed": 1
            },
            {
                "expires": 105679,
                "id": 149,
                "speed": 1
            },
            {
                "expires": 106647,
                "id": 151,
                "speed": 1
            },
            {
                "expires": 108744,
                "id": 155,
                "speed": 1
            },
            {
                "expires": 108905,
                "id": 156,
                "speed": 1
            },
            {
                "expires": 109711,
                "id": 159,
                "speed": 1
            },
            {
                "expires": 109873,
                "id": 160,
                "speed": 1
            }
        ],
        [
            {
                "expires": 19550,
                "id": 1,
                "speed": 1
            },
            {
                "expires": 22131,
                "id": 3,
                "speed": 1
            },
            {
                "expires": 22776,
                "id": 5,
                "speed": 1
            },
            {
                "expires": 24711,
                "id": 7,
                "speed": 1
            },
            {
                "expires": 26969,
                "id": 10,
                "speed": 1
            },
            {
                "expires": 29873,
                "id": 13,
                "speed": 1
            },
            {
                "expires": 32453,
                "id": 15,
                "speed": 1
            },
            {
                "expires": 33744,
                "id": 16,
                "speed": 1
            },
            {
                "expires": 36324,
                "id": 18,
                "speed": 1
            },
            {
                "expires": 37615,
                "id": 20,
                "speed": 1
            },
            {
                "expires": 38905,
                "id": 21,
                "speed": 1
            },
            {
                "expires": 45357,
                "id": 26,
                "speed": 1
            },
            {
                "expires": 51808,
                "id": 32,
                "speed": 1
            },
            {
                "expires": 52292,
                "id": 33,
                "speed": 1
            },
            {
                "expires": 52776,
                "id": 34,
                "speed": 1
            },
            {
                "expires": 54066,
                "id": 36,
                "speed": 1
            },
            {
                "expires": 55357,
                "id": 40,
                "speed": 1
            },
            {
                "expires": 56324,
                "id": 42,
                "speed": 1
            },
            {
                "expires": 56969,
                "id": 44,
                "speed": 1
            },
            {
                "expires": 57615,
                "id": 46,
                "speed": 1
            },
            {
                "expires": 58260,
                "id": 49,
                "speed": 1
            },
            {
                "expires": 61808,
                "id": 58,
                "speed": 1
            },
            {
                "expires": 62131,
                "id": 59,
                "speed": 1
            },
            {
                "expires": 63421,
                "id": 63,
                "speed": 1
            },
            {
                "expires": 63744,
                "id": 64,
                "speed": 1
            },
            {
                "expires": 64066,
                "id": 65,
                "speed": 1
            },
            {
                "expires": 64711,
                "id": 66,
                "speed": 1
            },
            {
                "expires": 66002,
                "id": 68,
                "speed": 1
            },
            {
                "expires": 66324,
                "id": 70,
                "speed": 1
            },
            {
                "expires": 66647,
                "id": 73,
                "speed": 1
            },
            {
                "expires": 68260,
                "id": 77,
                "speed": 1
            },
            {
                "expires": 68905,
                "id": 80,
                "speed": 1
            },
            {
                "expires": 70518,
                "id": 84,
                "speed": 1
            },
            {
                "expires": 71808,
                "id": 86,
                "speed": 1
            },
            {
                "expires": 72776,
                "id": 88,
                "speed": 1
            },
            {
                "expires": 73744,
                "id": 92,
                "speed": 1
            },
            {
                "expires": 75679,
                "id": 96,
                "speed": 1
            },
            {
                "expires": 76969,
                "id": 98,
                "speed": 1
            },
            {
                "expires": 77937,
                "id": 100,
                "speed": 1
            },
            {
                "expires": 79228,
                "id": 104,
                "speed": 1
            },
            {
                "expires": 80195,
                "id": 106,
                "speed": 1
            },
            {
                "expires": 81486,
                "id": 108,
                "speed": 1
            },
            {
                "expires": 82776,
                "id": 110,
                "speed": 1
            },
            {
                "expires": 84066,
                "id": 112,
                "speed": 1
            },
            {
                "expires": 88582,
                "id": 121,
                "speed": 1
            },
            {
                "expires": 89228,
                "id": 123,
                "speed": 1
            },
            {
                "expires": 89873,
                "id": 127,
                "speed": 1
            },
            {
                "expires": 91808,
                "id": 130,
                "speed": 1
            },
            {
                "expires": 95034,
                "id": 133,
                "speed": 1
            },
            {
                "expires": 96808,
                "id": 139,
                "speed": 1
            },
            {
                "expires": 96969,
                "id": 140,
                "speed": 1
            },
            {
                "expires": 97292,
                "id": 141,
                "speed": 1
            },
            {
                "expires": 99228,
                "id": 144,
                "speed": 1
            },
            {
                "expires": 103099,
                "id": 147,
                "speed": 1
            },
            {
                "expires": 106163,
                "id": 150,
                "speed": 1
            },
            {
                "expires": 107131,
                "id": 152,
                "speed": 1
            },
            {
                "expires": 108260,
                "id": 153,
                "speed": 1
            },
            {
                "expires": 108421,
                "id": 154,
                "speed": 1
            },
            {
                "expires": 109228,
                "id": 157,
                "speed": 1
            },
            {
                "expires": 109389,
                "id": 158,
                "speed": 1
            }
        ],
        [
            {
                "expires": 27453,
                "id": 11,
                "speed": 1
            },
            {
                "expires": 41486,
                "id": 23,
                "speed": 1
            },
            {
                "expires": 46647,
                "id": 27,
                "speed": 1
            },
            {
                "expires": 53744,
                "id": 35,
                "speed": 1
            },
            {
                "expires": 55679,
                "id": 41,
                "speed": 1
            },
            {
                "expires": 58905,
                "id": 50,
                "speed": 1
            },
            {
                "expires": 67615,
                "id": 75,
                "speed": 1
            },
            {
                "expires": 69228,
                "id": 82,
                "speed": 1
            },
            {
                "expires": 73421,
                "id": 90,
                "speed": 1
            },
            {
                "expires": 74389,
                "id": 94,
                "speed": 1
            },
            {
                "expires": 78260,
                "id": 101,
                "speed": 1
            },
            {
                "expires": 78905,
                "id": 103,
                "speed": 1
            },
            {
                "expires": 85357,
                "id": 115,
                "speed": 1
            },
            {
                "expires": 86647,
                "id": 117,
                "speed": 1
            },
            {
                "expires": 88905,
                "id": 122,
                "speed": 1
            },
            {
                "expires": 89550,
                "id": 125,
                "speed": 1
            },
            {
                "expires": 96002,
                "id": 136,
                "speed": 1
            },
            {
                "expires": 104389,
                "id": 148,
                "speed": 1
            }
        ]
    ],
    "slideNotes": []
}